climaemet/__init__.py
climaemet/climaemet.py
climaemet-0.1.0.dist-info/LICENSE.txt
climaemet-0.1.0.dist-info/METADATA
climaemet-0.1.0.dist-info/WHEEL
climaemet-0.1.0.dist-info/top_level.txt
climaemet-0.1.0.dist-info/RECORD
